mcp2anp/__init__.py
mcp2anp/__main__.py
mcp2anp/server.py
mcp2anp/server_http.py
mcp2anp/server_remote.py
mcp2anp/core/__init__.py
mcp2anp/core/handlers.py
mcp2anp/utils/__init__.py
mcp2anp/utils/logging.py
mcp2anp/utils/models.py
mcp2anp-0.1.0.dist-info/licenses/LICENSE
mcp2anp-0.1.0.dist-info/METADATA
mcp2anp-0.1.0.dist-info/WHEEL
mcp2anp-0.1.0.dist-info/entry_points.txt
mcp2anp-0.1.0.dist-info/top_level.txt
mcp2anp-0.1.0.dist-info/RECORD
