Metadata-Version: 2.4
Name: mcp2anp
Version: 0.1.0
Summary: MCP server that converts MCP protocol to ANP protocol
Author-email: mcp2anp Team <dev@example.com>
License: MIT
Project-URL: Homepage, https://github.com/example/mcp2anp
Project-URL: Repository, https://github.com/example/mcp2anp
Project-URL: Issues, https://github.com/example/mcp2anp/issues
Classifier: Development Status :: 3 - Alpha
Classifier: Intended Audience :: Developers
Classifier: License :: OSI Approved :: MIT License
Classifier: Programming Language :: Python :: 3
Classifier: Programming Language :: Python :: 3.11
Classifier: Programming Language :: Python :: 3.12
Requires-Python: >=3.11
License-File: LICENSE
Requires-Dist: pydantic>=2.5.0
Requires-Dist: click>=8.1.0
Requires-Dist: structlog>=23.1.0
Requires-Dist: mcp>=1.0.0
Requires-Dist: anp>=0.4.3
Requires-Dist: fastapi>=0.104.0
Requires-Dist: starlette>=0.27.0
Requires-Dist: uvicorn[standard]>=0.24.0
Requires-Dist: httpx>=0.27.0
Requires-Dist: fastmcp>=2.12.4
Dynamic: license-file
